[
  {
    "timestamp": 1769115600000,
    "open": 89370.8,
    "high": 89556.2,
    "low": 89336.6,
    "close": 89340.8,
    "volume": 228.386
  },
  {
    "timestamp": 1769115900000,
    "open": 89340.8,
    "high": 89545.8,
    "low": 89340.8,
    "close": 89538.8,
    "volume": 148.558
  },
  {
    "timestamp": 1769116200000,
    "open": 89538.8,
    "high": 89595,
    "low": 89500,
    "close": 89500.1,
    "volume": 90.052
  },
  {
    "timestamp": 1769116500000,
    "open": 89500.1,
    "high": 89607.3,
    "low": 89500,
    "close": 89594.1,
    "volume": 199.737
  },
  {
    "timestamp": 1769116800000,
    "open": 89594.2,
    "high": 89634.7,
    "low": 89572.5,
    "close": 89589.2,
    "volume": 126.773
  },
  {
    "timestamp": 1769117100000,
    "open": 89589.3,
    "high": 89589.4,
    "low": 89519.5,
    "close": 89534.5,
    "volume": 174.825
  },
  {
    "timestamp": 1769117400000,
    "open": 89534.4,
    "high": 89567.8,
    "low": 89457,
    "close": 89495.9,
    "volume": 200.191
  },
  {
    "timestamp": 1769117700000,
    "open": 89495.9,
    "high": 89519.2,
    "low": 89466.4,
    "close": 89466.4,
    "volume": 78.217
  },
  {
    "timestamp": 1769118000000,
    "open": 89466.4,
    "high": 89476.3,
    "low": 89347,
    "close": 89347.1,
    "volume": 106.235
  },
  {
    "timestamp": 1769118300000,
    "open": 89347,
    "high": 89347.1,
    "low": 89200.9,
    "close": 89301.9,
    "volume": 435.303
  },
  {
    "timestamp": 1769118600000,
    "open": 89302,
    "high": 89339.8,
    "low": 89277.9,
    "close": 89324.4,
    "volume": 79.314
  },
  {
    "timestamp": 1769118900000,
    "open": 89324.4,
    "high": 89336.4,
    "low": 89200,
    "close": 89222.1,
    "volume": 345.404
  },
  {
    "timestamp": 1769119200000,
    "open": 89222.2,
    "high": 89235,
    "low": 89095.5,
    "close": 89208.4,
    "volume": 614.536
  },
  {
    "timestamp": 1769119500000,
    "open": 89208.3,
    "high": 89304.8,
    "low": 89176.7,
    "close": 89262.2,
    "volume": 334.58
  },
  {
    "timestamp": 1769119800000,
    "open": 89262.2,
    "high": 89535.1,
    "low": 89245.4,
    "close": 89452.2,
    "volume": 306.548
  },
  {
    "timestamp": 1769120100000,
    "open": 89452.3,
    "high": 89490.5,
    "low": 89322.5,
    "close": 89322.5,
    "volume": 202.658
  },
  {
    "timestamp": 1769120400000,
    "open": 89322.6,
    "high": 89379,
    "low": 89322.5,
    "close": 89363.7,
    "volume": 55.867
  },
  {
    "timestamp": 1769120700000,
    "open": 89363.6,
    "high": 89450,
    "low": 89343,
    "close": 89380.2,
    "volume": 144.919
  },
  {
    "timestamp": 1769121000000,
    "open": 89380.1,
    "high": 89383.8,
    "low": 89206.4,
    "close": 89206.4,
    "volume": 110.412
  },
  {
    "timestamp": 1769121300000,
    "open": 89206.5,
    "high": 89256.2,
    "low": 89183.1,
    "close": 89192.5,
    "volume": 148.404
  },
  {
    "timestamp": 1769121600000,
    "open": 89192.5,
    "high": 89243,
    "low": 89128,
    "close": 89221.6,
    "volume": 164.695
  },
  {
    "timestamp": 1769121900000,
    "open": 89221.5,
    "high": 89327.8,
    "low": 89221.5,
    "close": 89307,
    "volume": 215.506
  },
  {
    "timestamp": 1769122200000,
    "open": 89307,
    "high": 89336.5,
    "low": 89267.8,
    "close": 89336.4,
    "volume": 69.756
  },
  {
    "timestamp": 1769122500000,
    "open": 89336.4,
    "high": 89336.4,
    "low": 89272,
    "close": 89304.7,
    "volume": 100.363
  },
  {
    "timestamp": 1769122800000,
    "open": 89304.7,
    "high": 89336.6,
    "low": 89127.8,
    "close": 89140,
    "volume": 326.286
  },
  {
    "timestamp": 1769123100000,
    "open": 89140.1,
    "high": 89255.7,
    "low": 89124.8,
    "close": 89247.8,
    "volume": 171.607
  },
  {
    "timestamp": 1769123400000,
    "open": 89247.7,
    "high": 89267.1,
    "low": 89182.7,
    "close": 89262.8,
    "volume": 165.278
  },
  {
    "timestamp": 1769123700000,
    "open": 89262.9,
    "high": 89362.8,
    "low": 89252.9,
    "close": 89303.8,
    "volume": 95.557
  },
  {
    "timestamp": 1769124000000,
    "open": 89303.8,
    "high": 89396.6,
    "low": 89303.7,
    "close": 89396.5,
    "volume": 143.443
  },
  {
    "timestamp": 1769124300000,
    "open": 89396.5,
    "high": 89480,
    "low": 89368.5,
    "close": 89399.6,
    "volume": 173.479
  },
  {
    "timestamp": 1769124600000,
    "open": 89399.6,
    "high": 89554.2,
    "low": 89365.2,
    "close": 89528.3,
    "volume": 157.75
  },
  {
    "timestamp": 1769124900000,
    "open": 89528.4,
    "high": 89534.9,
    "low": 89472.9,
    "close": 89473,
    "volume": 124.115
  },
  {
    "timestamp": 1769125200000,
    "open": 89472.9,
    "high": 89478.7,
    "low": 89430.8,
    "close": 89461.7,
    "volume": 75.714
  },
  {
    "timestamp": 1769125500000,
    "open": 89461.7,
    "high": 89506.7,
    "low": 89461.7,
    "close": 89506.7,
    "volume": 50.38
  },
  {
    "timestamp": 1769125800000,
    "open": 89506.7,
    "high": 89511.4,
    "low": 89467.4,
    "close": 89491.6,
    "volume": 70.49
  },
  {
    "timestamp": 1769126100000,
    "open": 89491.7,
    "high": 89519.7,
    "low": 89464.1,
    "close": 89518.5,
    "volume": 111.459
  },
  {
    "timestamp": 1769126400000,
    "open": 89518.4,
    "high": 89518.5,
    "low": 89447.2,
    "close": 89456.1,
    "volume": 152.761
  },
  {
    "timestamp": 1769126700000,
    "open": 89456.2,
    "high": 89476,
    "low": 89400,
    "close": 89476,
    "volume": 141.731
  },
  {
    "timestamp": 1769127000000,
    "open": 89476,
    "high": 89518.4,
    "low": 89475.2,
    "close": 89500,
    "volume": 74.221
  },
  {
    "timestamp": 1769127300000,
    "open": 89500,
    "high": 89595.7,
    "low": 89488.5,
    "close": 89579.3,
    "volume": 153.709
  },
  {
    "timestamp": 1769127600000,
    "open": 89579.4,
    "high": 89600,
    "low": 89551,
    "close": 89576.2,
    "volume": 118.65
  },
  {
    "timestamp": 1769127900000,
    "open": 89576.1,
    "high": 89576.2,
    "low": 89532,
    "close": 89565.6,
    "volume": 62.795
  },
  {
    "timestamp": 1769128200000,
    "open": 89565.7,
    "high": 89583.3,
    "low": 89518.3,
    "close": 89529.4,
    "volume": 76.859
  },
  {
    "timestamp": 1769128500000,
    "open": 89529.5,
    "high": 89542,
    "low": 89464.5,
    "close": 89532.6,
    "volume": 79.713
  },
  {
    "timestamp": 1769128800000,
    "open": 89532.7,
    "high": 89553.7,
    "low": 89502.8,
    "close": 89515.8,
    "volume": 66.064
  },
  {
    "timestamp": 1769129100000,
    "open": 89515.8,
    "high": 89544.7,
    "low": 89480.2,
    "close": 89544.6,
    "volume": 97.396
  },
  {
    "timestamp": 1769129400000,
    "open": 89544.7,
    "high": 89576,
    "low": 89523.2,
    "close": 89569.1,
    "volume": 95.79
  },
  {
    "timestamp": 1769129700000,
    "open": 89569.2,
    "high": 89573.5,
    "low": 89477,
    "close": 89484.6,
    "volume": 241.652
  },
  {
    "timestamp": 1769130000000,
    "open": 89484.6,
    "high": 89622,
    "low": 89484.6,
    "close": 89602.5,
    "volume": 136.156
  },
  {
    "timestamp": 1769130300000,
    "open": 89602.5,
    "high": 89602.5,
    "low": 89538.4,
    "close": 89587.6,
    "volume": 107.611
  },
  {
    "timestamp": 1769130600000,
    "open": 89587.6,
    "high": 89645.3,
    "low": 89540.4,
    "close": 89558.4,
    "volume": 144.79
  },
  {
    "timestamp": 1769130900000,
    "open": 89558.4,
    "high": 89647,
    "low": 89558.4,
    "close": 89625.8,
    "volume": 103.455
  },
  {
    "timestamp": 1769131200000,
    "open": 89625.8,
    "high": 89650,
    "low": 89607.6,
    "close": 89615.2,
    "volume": 103.343
  },
  {
    "timestamp": 1769131500000,
    "open": 89615.2,
    "high": 89664.1,
    "low": 89574.8,
    "close": 89653.6,
    "volume": 165.315
  },
  {
    "timestamp": 1769131800000,
    "open": 89653.7,
    "high": 89778.7,
    "low": 89600.1,
    "close": 89759.4,
    "volume": 343.074
  },
  {
    "timestamp": 1769132100000,
    "open": 89759.4,
    "high": 89828.7,
    "low": 89712.8,
    "close": 89794.5,
    "volume": 282.989
  },
  {
    "timestamp": 1769132400000,
    "open": 89794.5,
    "high": 89813.4,
    "low": 89765.9,
    "close": 89781.6,
    "volume": 81.581
  },
  {
    "timestamp": 1769132700000,
    "open": 89781.5,
    "high": 89781.6,
    "low": 89726.7,
    "close": 89765.8,
    "volume": 147.002
  },
  {
    "timestamp": 1769133000000,
    "open": 89765.7,
    "high": 89830.9,
    "low": 89765.7,
    "close": 89823,
    "volume": 113.981
  },
  {
    "timestamp": 1769133300000,
    "open": 89823.1,
    "high": 89900,
    "low": 89797.3,
    "close": 89893.7,
    "volume": 267.001
  },
  {
    "timestamp": 1769133600000,
    "open": 89893.7,
    "high": 89948.9,
    "low": 89779.6,
    "close": 89779.6,
    "volume": 430.449
  },
  {
    "timestamp": 1769133900000,
    "open": 89779.7,
    "high": 89818.2,
    "low": 89751.3,
    "close": 89764.6,
    "volume": 146.73
  },
  {
    "timestamp": 1769134200000,
    "open": 89764.6,
    "high": 89910.7,
    "low": 89764.5,
    "close": 89905,
    "volume": 278.835
  },
  {
    "timestamp": 1769134500000,
    "open": 89905,
    "high": 89905,
    "low": 89794.7,
    "close": 89832,
    "volume": 103.807
  },
  {
    "timestamp": 1769134800000,
    "open": 89832,
    "high": 89832.1,
    "low": 89764.2,
    "close": 89769.2,
    "volume": 92.511
  },
  {
    "timestamp": 1769135100000,
    "open": 89769.2,
    "high": 89779.5,
    "low": 89683,
    "close": 89722,
    "volume": 161.916
  },
  {
    "timestamp": 1769135400000,
    "open": 89722,
    "high": 89778.9,
    "low": 89715.3,
    "close": 89763.9,
    "volume": 104.132
  },
  {
    "timestamp": 1769135700000,
    "open": 89763.9,
    "high": 89789.9,
    "low": 89743,
    "close": 89772.3,
    "volume": 237.754
  },
  {
    "timestamp": 1769136000000,
    "open": 89772.2,
    "high": 89788.3,
    "low": 89701,
    "close": 89740.7,
    "volume": 137.023
  },
  {
    "timestamp": 1769136300000,
    "open": 89740.8,
    "high": 89771.9,
    "low": 89690.6,
    "close": 89693.7,
    "volume": 89.092
  },
  {
    "timestamp": 1769136600000,
    "open": 89693.7,
    "high": 89699.9,
    "low": 89655,
    "close": 89655.1,
    "volume": 130.615
  },
  {
    "timestamp": 1769136900000,
    "open": 89655,
    "high": 89655.1,
    "low": 89605,
    "close": 89611.2,
    "volume": 209.259
  },
  {
    "timestamp": 1769137200000,
    "open": 89611.3,
    "high": 89685.1,
    "low": 89590.5,
    "close": 89672.4,
    "volume": 256.241
  },
  {
    "timestamp": 1769137500000,
    "open": 89672.4,
    "high": 89753.3,
    "low": 89629.9,
    "close": 89740,
    "volume": 158.818
  },
  {
    "timestamp": 1769137800000,
    "open": 89740,
    "high": 89768.3,
    "low": 89733.6,
    "close": 89768.3,
    "volume": 78.368
  },
  {
    "timestamp": 1769138100000,
    "open": 89768.2,
    "high": 89860,
    "low": 89755.5,
    "close": 89828.8,
    "volume": 283.734
  },
  {
    "timestamp": 1769138400000,
    "open": 89828.8,
    "high": 89860.6,
    "low": 89815.4,
    "close": 89846.4,
    "volume": 130.414
  },
  {
    "timestamp": 1769138700000,
    "open": 89846.3,
    "high": 89875.2,
    "low": 89846.3,
    "close": 89851,
    "volume": 79.698
  },
  {
    "timestamp": 1769139000000,
    "open": 89851,
    "high": 89887.3,
    "low": 89800,
    "close": 89807.7,
    "volume": 164.799
  },
  {
    "timestamp": 1769139300000,
    "open": 89807.8,
    "high": 89819.9,
    "low": 89757.3,
    "close": 89809,
    "volume": 148.111
  },
  {
    "timestamp": 1769139600000,
    "open": 89809,
    "high": 89850,
    "low": 89809,
    "close": 89850,
    "volume": 66.968
  },
  {
    "timestamp": 1769139900000,
    "open": 89850,
    "high": 89872,
    "low": 89821.6,
    "close": 89849.5,
    "volume": 68.369
  },
  {
    "timestamp": 1769140200000,
    "open": 89849.5,
    "high": 89878.4,
    "low": 89849.4,
    "close": 89864.5,
    "volume": 85.277
  },
  {
    "timestamp": 1769140500000,
    "open": 89864.4,
    "high": 89886.2,
    "low": 89814.4,
    "close": 89886.1,
    "volume": 102.751
  },
  {
    "timestamp": 1769140800000,
    "open": 89886.2,
    "high": 89888,
    "low": 89838.1,
    "close": 89840.5,
    "volume": 141.086
  },
  {
    "timestamp": 1769141100000,
    "open": 89840.5,
    "high": 89865.2,
    "low": 89835.4,
    "close": 89865.1,
    "volume": 59.079
  },
  {
    "timestamp": 1769141400000,
    "open": 89865.1,
    "high": 90046.6,
    "low": 89865.1,
    "close": 90034.6,
    "volume": 690.664
  },
  {
    "timestamp": 1769141700000,
    "open": 90034.6,
    "high": 90050,
    "low": 89915.5,
    "close": 89931.9,
    "volume": 276.41
  },
  {
    "timestamp": 1769142000000,
    "open": 89932,
    "high": 89967.5,
    "low": 89914.8,
    "close": 89945.5,
    "volume": 139.76
  },
  {
    "timestamp": 1769142300000,
    "open": 89945.4,
    "high": 89973.9,
    "low": 89927.9,
    "close": 89939.5,
    "volume": 116.032
  },
  {
    "timestamp": 1769142600000,
    "open": 89939.4,
    "high": 90000,
    "low": 89870,
    "close": 90000,
    "volume": 227.969
  },
  {
    "timestamp": 1769142900000,
    "open": 90000,
    "high": 90000,
    "low": 89923,
    "close": 89937.2,
    "volume": 102.596
  },
  {
    "timestamp": 1769143200000,
    "open": 89937.2,
    "high": 89961.1,
    "low": 89927.1,
    "close": 89935.9,
    "volume": 101.934
  },
  {
    "timestamp": 1769143500000,
    "open": 89935.9,
    "high": 89994.6,
    "low": 89929.8,
    "close": 89929.8,
    "volume": 154.497
  },
  {
    "timestamp": 1769143800000,
    "open": 89929.9,
    "high": 89965.6,
    "low": 89929.8,
    "close": 89951,
    "volume": 116.202
  },
  {
    "timestamp": 1769144100000,
    "open": 89951,
    "high": 89968.5,
    "low": 89922.5,
    "close": 89922.5,
    "volume": 173.53
  },
  {
    "timestamp": 1769144400000,
    "open": 89922.6,
    "high": 89928.3,
    "low": 89850,
    "close": 89864.8,
    "volume": 173.427
  },
  {
    "timestamp": 1769144700000,
    "open": 89864.9,
    "high": 89864.9,
    "low": 89822.1,
    "close": 89839.4,
    "volume": 171.146
  },
  {
    "timestamp": 1769145000000,
    "open": 89839.4,
    "high": 89851.5,
    "low": 89814,
    "close": 89844.5,
    "volume": 146.697
  },
  {
    "timestamp": 1769145300000,
    "open": 89844.6,
    "high": 89844.6,
    "low": 89778.8,
    "close": 89778.8,
    "volume": 149.638
  },
  {
    "timestamp": 1769145600000,
    "open": 89778.9,
    "high": 89791.6,
    "low": 89586.4,
    "close": 89594.8,
    "volume": 417.788
  },
  {
    "timestamp": 1769145900000,
    "open": 89594.9,
    "high": 89622,
    "low": 89481,
    "close": 89603.5,
    "volume": 836.57
  },
  {
    "timestamp": 1769146200000,
    "open": 89603.5,
    "high": 89663.2,
    "low": 89573.3,
    "close": 89658.1,
    "volume": 263.944
  },
  {
    "timestamp": 1769146500000,
    "open": 89658.1,
    "high": 89661.2,
    "low": 89577.4,
    "close": 89581.6,
    "volume": 163.415
  },
  {
    "timestamp": 1769146800000,
    "open": 89581.5,
    "high": 89650,
    "low": 89581.5,
    "close": 89597.6,
    "volume": 118.954
  },
  {
    "timestamp": 1769147100000,
    "open": 89597.7,
    "high": 89640.2,
    "low": 89513.3,
    "close": 89587.1,
    "volume": 288.73
  },
  {
    "timestamp": 1769147400000,
    "open": 89587.2,
    "high": 89587.2,
    "low": 89484.9,
    "close": 89516.5,
    "volume": 166.382
  },
  {
    "timestamp": 1769147700000,
    "open": 89516.5,
    "high": 89600,
    "low": 89434.4,
    "close": 89573.8,
    "volume": 321.462
  },
  {
    "timestamp": 1769148000000,
    "open": 89573.8,
    "high": 89640.3,
    "low": 89512.9,
    "close": 89640.3,
    "volume": 350.206
  },
  {
    "timestamp": 1769148300000,
    "open": 89640.3,
    "high": 89771.1,
    "low": 89640.2,
    "close": 89694,
    "volume": 351.673
  },
  {
    "timestamp": 1769148600000,
    "open": 89694,
    "high": 89717.7,
    "low": 89679.3,
    "close": 89695.1,
    "volume": 135.336
  },
  {
    "timestamp": 1769148900000,
    "open": 89695,
    "high": 89724.3,
    "low": 89665,
    "close": 89724.3,
    "volume": 76.95
  },
  {
    "timestamp": 1769149200000,
    "open": 89724.4,
    "high": 89724.4,
    "low": 89546.4,
    "close": 89546.5,
    "volume": 151.322
  },
  {
    "timestamp": 1769149500000,
    "open": 89546.5,
    "high": 89577.9,
    "low": 89358,
    "close": 89433.6,
    "volume": 610.515
  },
  {
    "timestamp": 1769149800000,
    "open": 89433.7,
    "high": 89541.6,
    "low": 89433.6,
    "close": 89531.4,
    "volume": 173.978
  },
  {
    "timestamp": 1769150100000,
    "open": 89531.4,
    "high": 89555,
    "low": 89433,
    "close": 89540.4,
    "volume": 271.837
  },
  {
    "timestamp": 1769150400000,
    "open": 89540.5,
    "high": 89628.1,
    "low": 89540.4,
    "close": 89609.6,
    "volume": 112.729
  },
  {
    "timestamp": 1769150700000,
    "open": 89609.5,
    "high": 89624.6,
    "low": 89544.9,
    "close": 89606.2,
    "volume": 149.24
  },
  {
    "timestamp": 1769151000000,
    "open": 89606.3,
    "high": 89606.3,
    "low": 89492.7,
    "close": 89494.1,
    "volume": 168.536
  },
  {
    "timestamp": 1769151300000,
    "open": 89494.1,
    "high": 89503,
    "low": 89455.4,
    "close": 89474.9,
    "volume": 138.565
  },
  {
    "timestamp": 1769151600000,
    "open": 89475,
    "high": 89515.2,
    "low": 89432.1,
    "close": 89500.5,
    "volume": 223.665
  },
  {
    "timestamp": 1769151900000,
    "open": 89500.5,
    "high": 89532,
    "low": 89466.7,
    "close": 89466.7,
    "volume": 217.613
  },
  {
    "timestamp": 1769152200000,
    "open": 89466.8,
    "high": 89525,
    "low": 89460,
    "close": 89514.7,
    "volume": 168.115
  },
  {
    "timestamp": 1769152500000,
    "open": 89514.7,
    "high": 89563.4,
    "low": 89511.8,
    "close": 89550.2,
    "volume": 141.34
  },
  {
    "timestamp": 1769152800000,
    "open": 89550.2,
    "high": 89653.5,
    "low": 89544.8,
    "close": 89614,
    "volume": 150.361
  },
  {
    "timestamp": 1769153100000,
    "open": 89614,
    "high": 89644.7,
    "low": 89600,
    "close": 89600,
    "volume": 104.071
  },
  {
    "timestamp": 1769153400000,
    "open": 89600.1,
    "high": 89640.8,
    "low": 89560.1,
    "close": 89600.1,
    "volume": 156.669
  },
  {
    "timestamp": 1769153700000,
    "open": 89600.1,
    "high": 89639.1,
    "low": 89557.6,
    "close": 89588,
    "volume": 184.784
  },
  {
    "timestamp": 1769154000000,
    "open": 89588,
    "high": 89592.9,
    "low": 89502.4,
    "close": 89537,
    "volume": 135.415
  },
  {
    "timestamp": 1769154300000,
    "open": 89537.1,
    "high": 89537.1,
    "low": 89400.1,
    "close": 89465.9,
    "volume": 294.941
  },
  {
    "timestamp": 1769154600000,
    "open": 89465.9,
    "high": 89519.7,
    "low": 89430,
    "close": 89501,
    "volume": 186.438
  },
  {
    "timestamp": 1769154900000,
    "open": 89501,
    "high": 89576.7,
    "low": 89484.6,
    "close": 89497.2,
    "volume": 178.438
  },
  {
    "timestamp": 1769155200000,
    "open": 89497.3,
    "high": 89544.8,
    "low": 89440.9,
    "close": 89544.7,
    "volume": 264.183
  },
  {
    "timestamp": 1769155500000,
    "open": 89544.7,
    "high": 89590.9,
    "low": 89544,
    "close": 89562.9,
    "volume": 174.327
  },
  {
    "timestamp": 1769155800000,
    "open": 89562.9,
    "high": 89562.9,
    "low": 89490.1,
    "close": 89511.2,
    "volume": 123.083
  },
  {
    "timestamp": 1769156100000,
    "open": 89511.2,
    "high": 89529.4,
    "low": 89442.4,
    "close": 89480,
    "volume": 117.952
  },
  {
    "timestamp": 1769156400000,
    "open": 89479.9,
    "high": 89489.9,
    "low": 89404.5,
    "close": 89442.6,
    "volume": 207.136
  },
  {
    "timestamp": 1769156700000,
    "open": 89442.5,
    "high": 89456.6,
    "low": 89285.5,
    "close": 89290.4,
    "volume": 547.665
  },
  {
    "timestamp": 1769157000000,
    "open": 89290.3,
    "high": 89362.2,
    "low": 89162.5,
    "close": 89173.7,
    "volume": 782.333
  },
  {
    "timestamp": 1769157300000,
    "open": 89173.7,
    "high": 89228.5,
    "low": 89099,
    "close": 89209.4,
    "volume": 925.106
  },
  {
    "timestamp": 1769157600000,
    "open": 89209.4,
    "high": 89342.4,
    "low": 89208,
    "close": 89318.8,
    "volume": 392.945
  },
  {
    "timestamp": 1769157900000,
    "open": 89318.8,
    "high": 89387.9,
    "low": 89172.8,
    "close": 89221.3,
    "volume": 265.435
  },
  {
    "timestamp": 1769158200000,
    "open": 89221.4,
    "high": 89248.1,
    "low": 89140.1,
    "close": 89180.2,
    "volume": 200.358
  },
  {
    "timestamp": 1769158500000,
    "open": 89180.2,
    "high": 89230.1,
    "low": 89148.6,
    "close": 89185.1,
    "volume": 182.712
  },
  {
    "timestamp": 1769158800000,
    "open": 89185.1,
    "high": 89298.9,
    "low": 89164.2,
    "close": 89284.8,
    "volume": 219.246
  },
  {
    "timestamp": 1769159100000,
    "open": 89284.7,
    "high": 89350,
    "low": 89272.3,
    "close": 89336.1,
    "volume": 185.104
  },
  {
    "timestamp": 1769159400000,
    "open": 89336.1,
    "high": 89340,
    "low": 89191.9,
    "close": 89191.9,
    "volume": 196.451
  },
  {
    "timestamp": 1769159700000,
    "open": 89191.9,
    "high": 89192,
    "low": 88939.3,
    "close": 89024.8,
    "volume": 1142.034
  },
  {
    "timestamp": 1769160000000,
    "open": 89024.8,
    "high": 89135.8,
    "low": 89009.4,
    "close": 89135.8,
    "volume": 315.202
  },
  {
    "timestamp": 1769160300000,
    "open": 89135.7,
    "high": 89155,
    "low": 89100,
    "close": 89126.7,
    "volume": 213.17
  },
  {
    "timestamp": 1769160600000,
    "open": 89127,
    "high": 89149.7,
    "low": 89000.1,
    "close": 89000.1,
    "volume": 265.074
  },
  {
    "timestamp": 1769160900000,
    "open": 89000,
    "high": 89135.1,
    "low": 88931.8,
    "close": 89079.5,
    "volume": 548.775
  },
  {
    "timestamp": 1769161200000,
    "open": 89079.5,
    "high": 89096.2,
    "low": 88955.8,
    "close": 88979.1,
    "volume": 276.82
  },
  {
    "timestamp": 1769161500000,
    "open": 88979,
    "high": 88980.2,
    "low": 88850,
    "close": 88972,
    "volume": 859.466
  },
  {
    "timestamp": 1769161800000,
    "open": 88972,
    "high": 88972.1,
    "low": 88890.8,
    "close": 88914.6,
    "volume": 230.204
  },
  {
    "timestamp": 1769162100000,
    "open": 88914.7,
    "high": 88970.4,
    "low": 88914.6,
    "close": 88939.9,
    "volume": 146.306
  },
  {
    "timestamp": 1769162400000,
    "open": 88940,
    "high": 89031,
    "low": 88913.1,
    "close": 89002.8,
    "volume": 312.375
  },
  {
    "timestamp": 1769162700000,
    "open": 89002.9,
    "high": 89014.1,
    "low": 88892.5,
    "close": 88938.1,
    "volume": 212.864
  },
  {
    "timestamp": 1769163000000,
    "open": 88938.1,
    "high": 89055.1,
    "low": 88823.3,
    "close": 89020.8,
    "volume": 315.554
  },
  {
    "timestamp": 1769163300000,
    "open": 89020.8,
    "high": 89082.9,
    "low": 88966.1,
    "close": 89056,
    "volume": 347.452
  },
  {
    "timestamp": 1769163600000,
    "open": 89056,
    "high": 89100,
    "low": 89050.5,
    "close": 89090.6,
    "volume": 289.523
  },
  {
    "timestamp": 1769163900000,
    "open": 89090.6,
    "high": 89090.6,
    "low": 89060,
    "close": 89070.3,
    "volume": 141.818
  },
  {
    "timestamp": 1769164200000,
    "open": 89070.3,
    "high": 89070.3,
    "low": 88944,
    "close": 88987,
    "volume": 322.776
  },
  {
    "timestamp": 1769164500000,
    "open": 88986.9,
    "high": 89064,
    "low": 88986.9,
    "close": 89053.5,
    "volume": 146.321
  },
  {
    "timestamp": 1769164800000,
    "open": 89053.5,
    "high": 89093.6,
    "low": 88990,
    "close": 89081.6,
    "volume": 184.34
  },
  {
    "timestamp": 1769165100000,
    "open": 89081.6,
    "high": 89120.3,
    "low": 89000,
    "close": 89029.6,
    "volume": 358.827
  },
  {
    "timestamp": 1769165400000,
    "open": 89029.7,
    "high": 89031.6,
    "low": 89000,
    "close": 89012.2,
    "volume": 68.703
  },
  {
    "timestamp": 1769165700000,
    "open": 89012.2,
    "high": 89028.8,
    "low": 88980,
    "close": 89016.6,
    "volume": 78.94
  },
  {
    "timestamp": 1769166000000,
    "open": 89016.6,
    "high": 89125,
    "low": 88966.7,
    "close": 89093.7,
    "volume": 349.038
  },
  {
    "timestamp": 1769166300000,
    "open": 89094.2,
    "high": 89188.2,
    "low": 89077.5,
    "close": 89140.5,
    "volume": 478.407
  },
  {
    "timestamp": 1769166600000,
    "open": 89140.5,
    "high": 89200,
    "low": 89135.6,
    "close": 89182.3,
    "volume": 300.671
  },
  {
    "timestamp": 1769166900000,
    "open": 89182.3,
    "high": 89231.8,
    "low": 89164.2,
    "close": 89196.8,
    "volume": 233.839
  },
  {
    "timestamp": 1769167200000,
    "open": 89196.8,
    "high": 89220.6,
    "low": 89167.6,
    "close": 89180.1,
    "volume": 144.277
  },
  {
    "timestamp": 1769167500000,
    "open": 89180,
    "high": 89240.8,
    "low": 89180,
    "close": 89194.5,
    "volume": 112.925
  },
  {
    "timestamp": 1769167800000,
    "open": 89194.4,
    "high": 89319,
    "low": 89189.4,
    "close": 89255.7,
    "volume": 285.514
  },
  {
    "timestamp": 1769168100000,
    "open": 89255.7,
    "high": 89280,
    "low": 89243.5,
    "close": 89266.9,
    "volume": 132.92
  },
  {
    "timestamp": 1769168400000,
    "open": 89266.9,
    "high": 89267,
    "low": 89211.6,
    "close": 89211.7,
    "volume": 113.336
  },
  {
    "timestamp": 1769168700000,
    "open": 89211.6,
    "high": 89237.4,
    "low": 89211.6,
    "close": 89218.8,
    "volume": 55.539
  },
  {
    "timestamp": 1769169000000,
    "open": 89218.9,
    "high": 89248.6,
    "low": 89200,
    "close": 89226.1,
    "volume": 74.418
  },
  {
    "timestamp": 1769169300000,
    "open": 89226,
    "high": 89226.1,
    "low": 89130,
    "close": 89171.2,
    "volume": 197.648
  },
  {
    "timestamp": 1769169600000,
    "open": 89171.3,
    "high": 89207.3,
    "low": 89154,
    "close": 89200,
    "volume": 96.107
  },
  {
    "timestamp": 1769169900000,
    "open": 89199.9,
    "high": 89213,
    "low": 89164.5,
    "close": 89213,
    "volume": 96.672
  },
  {
    "timestamp": 1769170200000,
    "open": 89213,
    "high": 89214.5,
    "low": 89120,
    "close": 89120,
    "volume": 144.348
  },
  {
    "timestamp": 1769170500000,
    "open": 89120,
    "high": 89122.1,
    "low": 89092.6,
    "close": 89106.4,
    "volume": 164.976
  },
  {
    "timestamp": 1769170800000,
    "open": 89106.4,
    "high": 89151.6,
    "low": 89089.7,
    "close": 89151.6,
    "volume": 120.649
  },
  {
    "timestamp": 1769171100000,
    "open": 89151.6,
    "high": 89151.6,
    "low": 89117.9,
    "close": 89128.6,
    "volume": 82.813
  },
  {
    "timestamp": 1769171400000,
    "open": 89128.7,
    "high": 89155.5,
    "low": 89108.9,
    "close": 89112.9,
    "volume": 79.067
  },
  {
    "timestamp": 1769171700000,
    "open": 89112.9,
    "high": 89145.9,
    "low": 89056.6,
    "close": 89138.7,
    "volume": 132.453
  },
  {
    "timestamp": 1769172000000,
    "open": 89138.8,
    "high": 89207.7,
    "low": 89115.2,
    "close": 89207.7,
    "volume": 112.534
  },
  {
    "timestamp": 1769172300000,
    "open": 89207.6,
    "high": 89265.6,
    "low": 89207.6,
    "close": 89257.2,
    "volume": 168.321
  },
  {
    "timestamp": 1769172600000,
    "open": 89257.3,
    "high": 89342,
    "low": 89257.2,
    "close": 89263.5,
    "volume": 229.934
  },
  {
    "timestamp": 1769172900000,
    "open": 89263.5,
    "high": 89287.7,
    "low": 89220,
    "close": 89220,
    "volume": 241.977
  },
  {
    "timestamp": 1769173200000,
    "open": 89220,
    "high": 89269,
    "low": 89189.8,
    "close": 89256,
    "volume": 237.283
  },
  {
    "timestamp": 1769173500000,
    "open": 89256.1,
    "high": 89308,
    "low": 89251.2,
    "close": 89281.9,
    "volume": 213.972
  },
  {
    "timestamp": 1769173800000,
    "open": 89282,
    "high": 89380,
    "low": 89281.9,
    "close": 89365.9,
    "volume": 162.268
  },
  {
    "timestamp": 1769174100000,
    "open": 89365.8,
    "high": 89388,
    "low": 89315.4,
    "close": 89325.7,
    "volume": 245.691
  },
  {
    "timestamp": 1769174400000,
    "open": 89325.6,
    "high": 89392.3,
    "low": 89260,
    "close": 89308.3,
    "volume": 499.352
  },
  {
    "timestamp": 1769174700000,
    "open": 89308.2,
    "high": 89310.1,
    "low": 89222.9,
    "close": 89222.9,
    "volume": 126.329
  },
  {
    "timestamp": 1769175000000,
    "open": 89223,
    "high": 89258.4,
    "low": 89202.6,
    "close": 89231.3,
    "volume": 146.098
  },
  {
    "timestamp": 1769175300000,
    "open": 89231.3,
    "high": 89286.3,
    "low": 89214.9,
    "close": 89232,
    "volume": 93.321
  },
  {
    "timestamp": 1769175600000,
    "open": 89232,
    "high": 89322,
    "low": 89202.1,
    "close": 89318.7,
    "volume": 97.265
  },
  {
    "timestamp": 1769175900000,
    "open": 89318.8,
    "high": 89411.2,
    "low": 89289.5,
    "close": 89343.6,
    "volume": 261.016
  },
  {
    "timestamp": 1769176200000,
    "open": 89343.6,
    "high": 89343.6,
    "low": 89265.3,
    "close": 89299.5,
    "volume": 84.024
  },
  {
    "timestamp": 1769176500000,
    "open": 89299.5,
    "high": 89330.3,
    "low": 89288.6,
    "close": 89310.6,
    "volume": 81.44
  },
  {
    "timestamp": 1769176800000,
    "open": 89310.5,
    "high": 89345,
    "low": 89206.9,
    "close": 89344.9,
    "volume": 148.972
  },
  {
    "timestamp": 1769177100000,
    "open": 89345,
    "high": 89406.9,
    "low": 89344.9,
    "close": 89388.4,
    "volume": 208.212
  },
  {
    "timestamp": 1769177400000,
    "open": 89388.4,
    "high": 89430.7,
    "low": 89386.7,
    "close": 89409,
    "volume": 202.802
  },
  {
    "timestamp": 1769177700000,
    "open": 89409,
    "high": 89460.1,
    "low": 89378.1,
    "close": 89437.7,
    "volume": 222.497
  },
  {
    "timestamp": 1769178000000,
    "open": 89437.7,
    "high": 89570,
    "low": 89401.4,
    "close": 89570,
    "volume": 893.329
  },
  {
    "timestamp": 1769178300000,
    "open": 89569.9,
    "high": 89689.8,
    "low": 89507.3,
    "close": 89638.2,
    "volume": 1267.738
  },
  {
    "timestamp": 1769178600000,
    "open": 89638.2,
    "high": 89691.7,
    "low": 89100.5,
    "close": 89104.7,
    "volume": 1626.086
  },
  {
    "timestamp": 1769178900000,
    "open": 89104.7,
    "high": 89167.1,
    "low": 88590.6,
    "close": 88620.4,
    "volume": 3531.767
  },
  {
    "timestamp": 1769179200000,
    "open": 88620.3,
    "high": 89039.1,
    "low": 88600,
    "close": 88926.1,
    "volume": 1732.307
  },
  {
    "timestamp": 1769179500000,
    "open": 88926.1,
    "high": 88981.2,
    "low": 88650,
    "close": 88760.9,
    "volume": 1161.466
  },
  {
    "timestamp": 1769179800000,
    "open": 88761.3,
    "high": 89099.1,
    "low": 88753,
    "close": 88873.4,
    "volume": 1003.873
  },
  {
    "timestamp": 1769180100000,
    "open": 88873.4,
    "high": 88999,
    "low": 88818.1,
    "close": 88976,
    "volume": 480.084
  },
  {
    "timestamp": 1769180400000,
    "open": 88976,
    "high": 89060,
    "low": 88888.5,
    "close": 89000.1,
    "volume": 818.8
  },
  {
    "timestamp": 1769180700000,
    "open": 89000,
    "high": 89047,
    "low": 88901.6,
    "close": 88927.8,
    "volume": 378.203
  },
  {
    "timestamp": 1769181000000,
    "open": 88927.7,
    "high": 89157.6,
    "low": 88725.7,
    "close": 88783.2,
    "volume": 740.029
  },
  {
    "timestamp": 1769181300000,
    "open": 88783.2,
    "high": 88865.8,
    "low": 88530,
    "close": 88757.7,
    "volume": 1322.518
  },
  {
    "timestamp": 1769181600000,
    "open": 88757.8,
    "high": 89250,
    "low": 88725.4,
    "close": 89020.7,
    "volume": 1460.119
  },
  {
    "timestamp": 1769181900000,
    "open": 89020.7,
    "high": 89150,
    "low": 88824.5,
    "close": 88931.1,
    "volume": 540.513
  },
  {
    "timestamp": 1769182200000,
    "open": 88931.1,
    "high": 89060.7,
    "low": 88884,
    "close": 88934,
    "volume": 466.1
  },
  {
    "timestamp": 1769182500000,
    "open": 88934,
    "high": 89247.2,
    "low": 88915.5,
    "close": 89182,
    "volume": 502.083
  },
  {
    "timestamp": 1769182800000,
    "open": 89182,
    "high": 89246.3,
    "low": 89133.7,
    "close": 89219.5,
    "volume": 460.075
  },
  {
    "timestamp": 1769183100000,
    "open": 89219.5,
    "high": 89847.2,
    "low": 89212.4,
    "close": 89810.1,
    "volume": 2244.509
  },
  {
    "timestamp": 1769183400000,
    "open": 89810.1,
    "high": 89810.1,
    "low": 89502.2,
    "close": 89588.1,
    "volume": 1280.049
  },
  {
    "timestamp": 1769183700000,
    "open": 89588.1,
    "high": 89750,
    "low": 89536.8,
    "close": 89711.2,
    "volume": 546.769
  },
  {
    "timestamp": 1769184000000,
    "open": 89711.2,
    "high": 89907.7,
    "low": 89623.4,
    "close": 89901.6,
    "volume": 1190.665
  },
  {
    "timestamp": 1769184300000,
    "open": 89901.7,
    "high": 89932.9,
    "low": 89685.5,
    "close": 89766.2,
    "volume": 908.527
  },
  {
    "timestamp": 1769184600000,
    "open": 89766.2,
    "high": 89786,
    "low": 89600,
    "close": 89709.7,
    "volume": 1129.118
  },
  {
    "timestamp": 1769184900000,
    "open": 89709.7,
    "high": 89726.2,
    "low": 89570.5,
    "close": 89688.7,
    "volume": 863.375
  },
  {
    "timestamp": 1769185200000,
    "open": 89688.6,
    "high": 89688.6,
    "low": 89572.6,
    "close": 89640.9,
    "volume": 625.116
  },
  {
    "timestamp": 1769185500000,
    "open": 89640.9,
    "high": 89680.1,
    "low": 89466.6,
    "close": 89528.5,
    "volume": 503.38
  },
  {
    "timestamp": 1769185800000,
    "open": 89528.5,
    "high": 89788.5,
    "low": 89438,
    "close": 89786.6,
    "volume": 596.1
  },
  {
    "timestamp": 1769186100000,
    "open": 89786.6,
    "high": 90225,
    "low": 89786.6,
    "close": 90155.8,
    "volume": 3197.767
  },
  {
    "timestamp": 1769186400000,
    "open": 90155.8,
    "high": 90400,
    "low": 90065.8,
    "close": 90233.1,
    "volume": 2062.095
  },
  {
    "timestamp": 1769186700000,
    "open": 90233,
    "high": 90404.7,
    "low": 90087.8,
    "close": 90390.6,
    "volume": 1259.537
  },
  {
    "timestamp": 1769187000000,
    "open": 90390.7,
    "high": 90455,
    "low": 90115,
    "close": 90194.3,
    "volume": 1466.332
  },
  {
    "timestamp": 1769187300000,
    "open": 90194.4,
    "high": 90200,
    "low": 90066.9,
    "close": 90079,
    "volume": 624.956
  },
  {
    "timestamp": 1769187600000,
    "open": 90079.1,
    "high": 90100,
    "low": 89950,
    "close": 90063,
    "volume": 755.824
  },
  {
    "timestamp": 1769187900000,
    "open": 90063,
    "high": 90075,
    "low": 89931.2,
    "close": 89961.5,
    "volume": 427.036
  },
  {
    "timestamp": 1769188200000,
    "open": 89961.5,
    "high": 90166.5,
    "low": 89961.5,
    "close": 90166.5,
    "volume": 406.861
  },
  {
    "timestamp": 1769188500000,
    "open": 90166.6,
    "high": 90347.6,
    "low": 90166.6,
    "close": 90331.2,
    "volume": 551.343
  },
  {
    "timestamp": 1769188800000,
    "open": 90331.1,
    "high": 90406.8,
    "low": 90242.2,
    "close": 90367,
    "volume": 574.344
  },
  {
    "timestamp": 1769189100000,
    "open": 90367.1,
    "high": 90968.4,
    "low": 90358.1,
    "close": 90945.1,
    "volume": 4397.93
  },
  {
    "timestamp": 1769189400000,
    "open": 90945.1,
    "high": 91030.6,
    "low": 90730,
    "close": 90802.8,
    "volume": 2823.753
  },
  {
    "timestamp": 1769189700000,
    "open": 90802.7,
    "high": 91195,
    "low": 90761,
    "close": 90928.2,
    "volume": 2181.799
  },
  {
    "timestamp": 1769190000000,
    "open": 90928.2,
    "high": 90967.7,
    "low": 90723.9,
    "close": 90795.9,
    "volume": 1352.97
  },
  {
    "timestamp": 1769190300000,
    "open": 90796,
    "high": 91025.9,
    "low": 90796,
    "close": 90876,
    "volume": 1116.741
  },
  {
    "timestamp": 1769190600000,
    "open": 90875.9,
    "high": 90876,
    "low": 90564.3,
    "close": 90566.6,
    "volume": 1034.345
  },
  {
    "timestamp": 1769190900000,
    "open": 90566.6,
    "high": 90704.9,
    "low": 90517.5,
    "close": 90576,
    "volume": 1262.75
  },
  {
    "timestamp": 1769191200000,
    "open": 90576,
    "high": 90714.3,
    "low": 90411.8,
    "close": 90714.2,
    "volume": 1003.855
  },
  {
    "timestamp": 1769191500000,
    "open": 90714.2,
    "high": 91003.5,
    "low": 90659,
    "close": 90917.6,
    "volume": 1125.118
  },
  {
    "timestamp": 1769191800000,
    "open": 90917.6,
    "high": 90950,
    "low": 90673.7,
    "close": 90706.4,
    "volume": 712.595
  },
  {
    "timestamp": 1769192100000,
    "open": 90706.5,
    "high": 90878.5,
    "low": 90596.9,
    "close": 90863.6,
    "volume": 456.085
  },
  {
    "timestamp": 1769192400000,
    "open": 90863.5,
    "high": 90915.6,
    "low": 90732.9,
    "close": 90849.6,
    "volume": 515.843
  },
  {
    "timestamp": 1769192700000,
    "open": 90849.6,
    "high": 90867.8,
    "low": 90735.5,
    "close": 90828.6,
    "volume": 418.383
  },
  {
    "timestamp": 1769193000000,
    "open": 90828.5,
    "high": 90986,
    "low": 90780,
    "close": 90789.9,
    "volume": 548.291
  },
  {
    "timestamp": 1769193300000,
    "open": 90790,
    "high": 90865.1,
    "low": 90741.5,
    "close": 90793.8,
    "volume": 382.22
  },
  {
    "timestamp": 1769193600000,
    "open": 90793.8,
    "high": 90816.7,
    "low": 90627.2,
    "close": 90700.8,
    "volume": 815.028
  },
  {
    "timestamp": 1769193900000,
    "open": 90700.9,
    "high": 90700.9,
    "low": 90530,
    "close": 90549.8,
    "volume": 681.807
  },
  {
    "timestamp": 1769194200000,
    "open": 90549.8,
    "high": 90636.2,
    "low": 90471.6,
    "close": 90519.1,
    "volume": 596.627
  },
  {
    "timestamp": 1769194500000,
    "open": 90519.2,
    "high": 90600,
    "low": 90447,
    "close": 90486.3,
    "volume": 399.561
  },
  {
    "timestamp": 1769194800000,
    "open": 90486.3,
    "high": 90499.5,
    "low": 90155.9,
    "close": 90275.6,
    "volume": 1571.222
  },
  {
    "timestamp": 1769195100000,
    "open": 90275.7,
    "high": 90460.6,
    "low": 90178.9,
    "close": 90410,
    "volume": 1350.769
  },
  {
    "timestamp": 1769195400000,
    "open": 90410,
    "high": 90414.9,
    "low": 90228.6,
    "close": 90228.6,
    "volume": 1222.681
  },
  {
    "timestamp": 1769195700000,
    "open": 90228.6,
    "high": 90230.6,
    "low": 89681.5,
    "close": 89929,
    "volume": 4647.888
  },
  {
    "timestamp": 1769196000000,
    "open": 89929,
    "high": 90122.8,
    "low": 89862.6,
    "close": 90039.7,
    "volume": 835.277
  },
  {
    "timestamp": 1769196300000,
    "open": 90039.8,
    "high": 90085.5,
    "low": 89721,
    "close": 89796,
    "volume": 685.634
  },
  {
    "timestamp": 1769196600000,
    "open": 89796.6,
    "high": 89809.2,
    "low": 89550,
    "close": 89618.1,
    "volume": 1304.664
  },
  {
    "timestamp": 1769196900000,
    "open": 89618,
    "high": 89838.7,
    "low": 89556,
    "close": 89709.9,
    "volume": 1101.458
  },
  {
    "timestamp": 1769197200000,
    "open": 89709.9,
    "high": 89845.9,
    "low": 89680.7,
    "close": 89830.1,
    "volume": 405.665
  },
  {
    "timestamp": 1769197500000,
    "open": 89830.1,
    "high": 89869.4,
    "low": 89679.1,
    "close": 89705.5,
    "volume": 437.725
  },
  {
    "timestamp": 1769197800000,
    "open": 89705.5,
    "high": 89877.5,
    "low": 89697.9,
    "close": 89877.5,
    "volume": 346.941
  },
  {
    "timestamp": 1769198100000,
    "open": 89877.5,
    "high": 89986.4,
    "low": 89865.5,
    "close": 89938.3,
    "volume": 451.737
  },
  {
    "timestamp": 1769198400000,
    "open": 89938.3,
    "high": 89941,
    "low": 89801,
    "close": 89898.6,
    "volume": 337.385
  },
  {
    "timestamp": 1769198700000,
    "open": 89898.7,
    "high": 90016.8,
    "low": 89854,
    "close": 89978.9,
    "volume": 453.907
  },
  {
    "timestamp": 1769199000000,
    "open": 89979,
    "high": 90124.1,
    "low": 89916.8,
    "close": 90071.3,
    "volume": 484.057
  },
  {
    "timestamp": 1769199300000,
    "open": 90071.3,
    "high": 90095.6,
    "low": 89989.5,
    "close": 90010.1,
    "volume": 322.36
  },
  {
    "timestamp": 1769199600000,
    "open": 90010.2,
    "high": 90013.7,
    "low": 89883.7,
    "close": 89885.3,
    "volume": 163.445
  },
  {
    "timestamp": 1769199900000,
    "open": 89885.3,
    "high": 89885.3,
    "low": 89762.7,
    "close": 89765.1,
    "volume": 257.608
  },
  {
    "timestamp": 1769200200000,
    "open": 89765,
    "high": 89765,
    "low": 89250,
    "close": 89364.3,
    "volume": 1819.828
  },
  {
    "timestamp": 1769200500000,
    "open": 89364.3,
    "high": 89445.3,
    "low": 89200,
    "close": 89319.9,
    "volume": 887.699
  },
  {
    "timestamp": 1769200800000,
    "open": 89320,
    "high": 89429.4,
    "low": 89315,
    "close": 89375.1,
    "volume": 403.451
  },
  {
    "timestamp": 1769201100000,
    "open": 89375,
    "high": 89382.4,
    "low": 89163.6,
    "close": 89320,
    "volume": 590.953
  },
  {
    "timestamp": 1769201400000,
    "open": 89320.1,
    "high": 89412.3,
    "low": 89206,
    "close": 89412.3,
    "volume": 562.321
  },
  {
    "timestamp": 1769201700000,
    "open": 89412.3,
    "high": 89413,
    "low": 89397,
    "close": 89401.6,
    "volume": 10.425
  }
]